mermaid_diagram/__init__.py
mermaid_diagram/packet.py
mermaid_diagram-0.1.2.dist-info/licenses/LICENSE
mermaid_diagram-0.1.2.dist-info/METADATA
mermaid_diagram-0.1.2.dist-info/WHEEL
mermaid_diagram-0.1.2.dist-info/top_level.txt
mermaid_diagram-0.1.2.dist-info/RECORD
