Metadata-Version: 2.4
Name: mermaid_diagram
Version: 0.1.2
Summary: Generate the string which represents a Mermaid diagram.
Author: mrBrutus
License-Expression: MIT
Project-URL: Repository, https://github.com/mrBrutus/mermaid_diagram.git
Project-URL: Changelog, https://github.com/mrBrutus/mermaid_diagram/blob/main/CHANGELOG.md
Project-URL: Issues, https://github.com/mrBrutus/mermaid_diagram/issues
Classifier: Development Status :: 3 - Alpha
Classifier: Intended Audience :: Developers
Classifier: Intended Audience :: Information Technology
Classifier: Topic :: Documentation
Classifier: Topic :: Text Processing :: Markup :: Markdown
Classifier: Programming Language :: Python :: 3
Requires-Python: >=3.12
License-File: LICENSE
Dynamic: license-file
